pymodaq_plugins_amplitude/__init__.py
pymodaq_plugins_amplitude/utils.py
pymodaq_plugins_amplitude/daq_move_plugins/__init__.py
pymodaq_plugins_amplitude/daq_viewer_plugins/__init__.py
pymodaq_plugins_amplitude/daq_viewer_plugins/plugins_0D/__init__.py
pymodaq_plugins_amplitude/daq_viewer_plugins/plugins_0D/daq_0Dviewer_AmplitudeSystemsCRC16.py
pymodaq_plugins_amplitude/daq_viewer_plugins/plugins_1D/__init__.py
pymodaq_plugins_amplitude/daq_viewer_plugins/plugins_2D/__init__.py
pymodaq_plugins_amplitude/daq_viewer_plugins/plugins_ND/__init__.py
pymodaq_plugins_amplitude/hardware/__init__.py
pymodaq_plugins_amplitude/hardware/amplitude/SY-3118.ini
pymodaq_plugins_amplitude/hardware/amplitude/__init__.py
pymodaq_plugins_amplitude/hardware/amplitude/amplitude_systems.py
pymodaq_plugins_amplitude/resources/__init__.py
pymodaq_plugins_amplitude/resources/config_template.toml
pymodaq_plugins_amplitude-1.0.0.dist-info/METADATA
pymodaq_plugins_amplitude-1.0.0.dist-info/WHEEL
pymodaq_plugins_amplitude-1.0.0.dist-info/entry_points.txt
pymodaq_plugins_amplitude-1.0.0.dist-info/licenses/LICENSE
pymodaq_plugins_amplitude-1.0.0.dist-info/RECORD
